ROA_package/ROA.py
ROA_package/__init__.py
ROA_Tong-0.0.5.dist-info/LICENSE
ROA_Tong-0.0.5.dist-info/METADATA
ROA_Tong-0.0.5.dist-info/WHEEL
ROA_Tong-0.0.5.dist-info/top_level.txt
ROA_Tong-0.0.5.dist-info/RECORD
