Metadata-Version: 2.1
Name: ROA-Tong
Version: 0.0.5
Summary: Generating Rectangluar Occlusion Attacks
Home-page: https://tongwu2020.github.io/tongwu/
Author: Tong Wu
Author-email: tongwu@wustl.edu
License: UNKNOWN
Platform: UNKNOWN
Classifier: Programming Language :: Python :: 3
Classifier: Operating System :: OS Independent
